aiida_gaussian_datatypes/__init__.py
aiida_gaussian_datatypes/groups.py
aiida_gaussian_datatypes/utils.py
aiida_gaussian_datatypes/basisset/__init__.py
aiida_gaussian_datatypes/basisset/cli.py
aiida_gaussian_datatypes/basisset/data.py
aiida_gaussian_datatypes/pseudopotential/__init__.py
aiida_gaussian_datatypes/pseudopotential/cli.py
aiida_gaussian_datatypes/pseudopotential/data.py
tests/__init__.py
tests/conftest.py
tests/test_basisset_data.py
tests/test_cli.py
tests/test_group.py
tests/test_pseudo_data.py
aiida_gaussian_datatypes-0.5.1.dist-info/AUTHORS.txt
aiida_gaussian_datatypes-0.5.1.dist-info/LICENSE
aiida_gaussian_datatypes-0.5.1.dist-info/METADATA
aiida_gaussian_datatypes-0.5.1.dist-info/WHEEL
aiida_gaussian_datatypes-0.5.1.dist-info/entry_points.txt
aiida_gaussian_datatypes-0.5.1.dist-info/top_level.txt
aiida_gaussian_datatypes-0.5.1.dist-info/RECORD
