Metadata-Version: 2.1
Name: aiida-gaussian-datatypes
Version: 0.5.1
Summary: AiiDA data plugin to manage gaussian datatypes (basis sets and pseudopotentials) as first-class citizens
Home-page: https://github.com/dev-zero/aiida-gaussian-datatypes
Author: Tiziano Müller
Author-email: tiziano.mueller@chem.uzh.ch
License: MIT License
Classifier: Programming Language :: Python :: 3.6
Classifier: Programming Language :: Python :: 3.7
Classifier: Programming Language :: Python :: 3.8
Classifier: Programming Language :: Python :: 3.9
Classifier: Development Status :: 4 - Beta
Classifier: License :: OSI Approved :: MIT License
Classifier: Operating System :: OS Independent
Classifier: Topic :: Software Development :: Libraries :: Python Modules
Classifier: Topic :: Scientific/Engineering :: Chemistry
Classifier: Intended Audience :: Science/Research
Classifier: Framework :: AiiDA
License-File: LICENSE
License-File: AUTHORS.txt
Requires-Dist: aiida-core (>=1.6.2)
Requires-Dist: cp2k-input-tools (>=0.8.0)
Provides-Extra: docs
Requires-Dist: sphinx ; extra == 'docs'
Requires-Dist: sphinx-click (>=2.2.0) ; extra == 'docs'
Requires-Dist: sphinxcontrib-contentui ; extra == 'docs'
Requires-Dist: sphinx-rtd-theme ; extra == 'docs'
Requires-Dist: sphinxcontrib-details-directive ; (python_version >= "3.0") and extra == 'docs'
Provides-Extra: pre-commit
Requires-Dist: pre-commit (>=2.0.1) ; extra == 'pre-commit'
Provides-Extra: testing
Requires-Dist: pytest (>=6.0) ; extra == 'testing'
Requires-Dist: pytest-cov ; extra == 'testing'
Requires-Dist: codecov (>=2.0.15) ; extra == 'testing'
Requires-Dist: pgtest (>=1.3.1,~=1.3) ; extra == 'testing'
